{"cameraMode":{"drawMode":0,"name":"Shaded","section":"Shading Mode"},"sceneLighting":false,"audioPlay":false,"sceneViewState":{"m_AlwaysRefresh":false,"showFog":true,"showSkybox":false,"showFlares":true,"showImageEffects":true,"showParticleSystems":true,"showVisualEffectGraphs":true,"m_FxEnabled":true},"in2DMode":false,"pivot":{"x":39.299503326416019,"y":26.440959930419923,"z":48.76734161376953},"rotation":{"x":0.2745946943759918,"y":0.15577338635921479,"z":-0.04512934014201164,"w":0.9477894902229309},"size":7.919673442840576,"orthographic":false}